pod_export/__init__.py
pod_export/exceptions.py
pod_export/json_schema.json
pod_export/pod_export.py
pod_export/services.json
pod_export/version.py
pod_export-1.0.1.dist-info/METADATA
pod_export-1.0.1.dist-info/WHEEL
pod_export-1.0.1.dist-info/top_level.txt
pod_export-1.0.1.dist-info/RECORD
